README.md
setup.cfg
setup.py
matrix/API.py
matrix/__init__.py
matrix/classes.py
matrix/client.py
matrix/constants.py
matrix/discord_like_classes.py
matrix/e2ee.py
matrix/exceptions.py
matrix/parsers.py
matrix/utils.py
matrix_chat.egg-info/PKG-INFO
matrix_chat.egg-info/SOURCES.txt
matrix_chat.egg-info/dependency_links.txt
matrix_chat.egg-info/requires.txt
matrix_chat.egg-info/top_level.txt