Metadata-Version: 1.2
Name: matrix-chat
Version: 0.0.1.1
Summary: A Python wrapper for the Matrix API
Home-page: https://github.com/wwhtrbbtt/matrix.py
Author: Peet
Author-email: matrix@peet.ws
License: MIT
Project-URL: Documentation, https://matrixpy.readthedocs.io/en/latest/
Project-URL: Issue tracker, https://github.com/wwhtrbbtt/matrix.py/issues
Platform: UNKNOWN
Classifier: Development Status :: 3 - Alpha
Classifier: License :: OSI Approved :: MIT License
Classifier: Intended Audience :: Developers
Classifier: Natural Language :: English
Classifier: Operating System :: OS Independent
Classifier: Programming Language :: Python :: 3.8
Classifier: Programming Language :: Python :: 3.9
Classifier: Topic :: Internet
Classifier: Topic :: Software Development :: Libraries
Classifier: Topic :: Software Development :: Libraries :: Python Modules
Classifier: Topic :: Utilities
Classifier: Typing :: Typed
Requires-Python: >=3.8.0
